gitlab_async_client/__init__.py
gitlab_async_client/client.py
gitlab_async_client/py.typed
gitlab_async_client/types/__init__.py
gitlab_async_client/types/base.py
gitlab_async_client/types/extend.py
gitlab_async_client/types/mr.py
gitlab_async_client/types/project.py
gitlab_async_client-1.0.0.dist-info/METADATA
gitlab_async_client-1.0.0.dist-info/WHEEL
gitlab_async_client-1.0.0.dist-info/licenses/LICENSE
gitlab_async_client-1.0.0.dist-info/RECORD
