Metadata-Version: 2.4
Name: gitlab-async-client
Version: 1.0.0
Summary: A simple asyncronous gitlab http client
Project-URL: Repository, https://github.com/Vladimir-Titov/gitlab-async-client
Project-URL: Issues, https://github.com/Vladimir-Titov/gitlab-async-client/issues
Author-email: vtitov <v.v.titov94@gmail.com>
License-File: LICENSE
Classifier: Development Status :: 4 - Beta
Classifier: Programming Language :: Python :: 3.12
Requires-Python: >=3.12
Requires-Dist: aiohttp>=3.11.11
Requires-Dist: arrow>=1.3.0
Requires-Dist: pydantic>=2.10.6
